[
{"a": "Reaching definitions", "h": "Forward dataflow", "d": "Dataflow analysis", "t": 1},
{"a": "Live variable analysis", "h": "Backward dataflow", "d": "Dataflow analysis", "t": 1},
{"a": "Available expressions", "h": "Forward must-analysis", "d": "Redundancy elimination", "t": 2},
{"a": "Very busy expressions", "h": "Backward must-analysis", "d": "Code hoisting", "t": 3},
{"a": "Constant propagation", "h": "Lattice dataflow", "d": "Compiler optimization", "t": 1},
{"a": "Sparse conditional constant propagation", "h": null, "d": "Compiler optimization", "t": 3},
{"a": "Worklist dataflow solver", "h": "Fixed-point iteration", "d": "Dataflow engine", "t": 2},
{"a": "Abstract interpretation", "h": "Galois-connection domains", "d": "Static analysis", "t": 2},
{"a": "Interval analysis", "h": "Widening and narrowing", "d": "Range analysis", "t": 3},
{"a": "Octagon abstract domain", "h": "Unit-two-variable inequalities", "d": "Range analysis", "t": 3},
{"a": "Polyhedral analysis", "h": null, "d": "Loop optimization", "t": 3},
{"a": "Andersen pointer analysis", "h": "Inclusion constraints", "d": "Points-to analysis", "t": 2},
{"a": "Steensgaard pointer analysis", "h": "Unification constraints", "d": "Points-to analysis", "t": 3},
{"a": "K-CFA", "h": "Call-string context abstraction", "d": "Points-to analysis", "t": 3},
{"a": "Escape analysis", "h": null, "d": "Allocation optimization", "t": 3},
{"a": "Taint analysis", "h": "Source-sink propagation", "d": "Security analysis", "t": 2},
{"a": "Datalog-based analysis", "h": "Declarative rule evaluation", "d": "Security analysis", "t": 3},
{"a": "Dominator analysis", "h": "Cooper-Harvey-Kennedy", "d": "Control-flow analysis", "t": 2},
{"a": "Natural loop detection", "h": "Back-edge dominators", "d": "Loop analysis", "t": 2},
{"a": "Havlak loop nesting", "h": "Irreducible-region handling", "d": "Loop analysis", "t": 3},
{"a": "Call graph construction", "h": "Rapid type analysis", "d": "Interprocedural analysis", "t": 3},
{"a": "Interprocedural dataflow", "h": "IFDS tabulation", "d": "Whole-program analysis", "t": 3},
{"a": "Symbolic execution", "h": "Path-condition solving", "d": "Test generation", "t": 2},
{"a": "Concolic testing", "h": "Concrete-symbolic mixing", "d": "Test generation", "t": 2},
{"a": "Bounded model checking", "h": "SAT unrolling", "d": "Verification", "t": 2},
{"a": "Explicit-state model checking", "h": "State-space exploration", "d": "Verification", "t": 2},
{"a": "Symbolic model checking", "h": "BDD state sets", "d": "Verification", "t": 3},
{"a": "Partial order reduction", "h": null, "d": "Concurrent verification", "t": 3},
{"a": "CEGAR", "h": "Counterexample-guided refinement", "d": "Abstraction refinement", "t": 3},
{"a": "Predicate abstraction", "h": null, "d": "Software verification", "t": 3},
{"a": "IC3", "h": "Property-directed reachability", "d": "Hardware verification", "t": 3},
{"a": "K-induction", "h": "Strengthened inductive unrolling", "d": "Hardware verification", "t": 3},
{"a": "Interpolation-based model checking", "h": "Craig interpolant overapproximation", "d": "Hardware verification", "t": 3},
{"a": "Hoare logic verification", "h": "Weakest precondition", "d": "Program proof", "t": 2},
{"a": "Separation logic", "h": "Frame-rule reasoning", "d": "Heap verification", "t": 3},
{"a": "Shape analysis", "h": "Three-valued logic abstraction", "d": "Heap verification", "t": 3},
{"a": "Bi-abduction", "h": "Compositional footprint inference", "d": "Heap verification", "t": 3},
{"a": "Type inference", "h": "Hindley-Milner unification", "d": "Static typing", "t": 1},
{"a": "Bidirectional type checking", "h": null, "d": "Type checking", "t": 3},
{"a": "Liquid type inference", "h": "Predicate-qualifier abstraction", "d": "Static typing", "t": 3},
{"a": "Data race detection", "h": "Happens-before vector clocks", "d": "Concurrency analysis", "t": 2},
{"a": "Data race detection", "h": "Lockset analysis", "d": "Concurrency analysis", "t": 3},
{"a": "Fuzzing", "h": "Coverage-guided mutation", "d": "Bug finding", "t": 2},
{"a": "Delta debugging", "h": "Minimizing failing input", "d": "Fault localization", "t": 2},
{"a": "Spectrum-based fault localization", "h": "Ochiai suspiciousness ranking", "d": "Fault localization", "t": 3},
{"a": "Program slicing", "h": "Dependence graph reachability", "d": "Debugging aid", "t": 3},
{"a": "Common subexpression elimination", "h": "Value numbering", "d": "Compiler optimization", "t": 2},
{"a": "Loop-invariant code motion", "h": null, "d": "Compiler optimization", "t": 2},
{"a": "Dead code elimination", "h": "Mark-and-sweep on IR", "d": "Compiler optimization", "t": 2},
{"a": "Partial redundancy elimination", "h": "Lazy code motion", "d": "Compiler optimization", "t": 3},
{"a": "Equality saturation", "h": "E-graph rewriting without phase ordering", "d": "Compiler optimization", "t": 3},
{"a": "Superoptimization", "h": "Stochastic instruction-sequence search", "d": "Compiler optimization", "t": 3},
{"a": "Cytron SSA construction", "h": "Dominance-frontier phi placement", "d": "SSA construction", "t": 2},
{"a": "Braun SSA construction", "h": "On-the-fly local value tracking", "d": "SSA construction", "t": 3}
]
