[
{"a": "User-based collaborative filtering", "h": "Cosine neighbor similarity", "d": "Recommendation", "t": 1},
{"a": "Item-based collaborative filtering", "h": "Adjusted cosine similarity", "d": "Recommendation", "t": 1},
{"a": "Matrix factorization", "h": "Stochastic gradient descent", "d": "Recommendation", "t": 1},
{"a": "Alternating least squares", "h": "Implicit-feedback weighting", "d": "Recommendation", "t": 1},
{"a": "SVD++", "h": "Implicit-feedback factors", "d": "Rating prediction", "t": 2},
{"a": "Bayesian personalized ranking", "h": "Pairwise ranking loss", "d": "Implicit recommendation", "t": 2},
{"a": "Factorization machines", "h": "Pairwise feature interactions", "d": "Sparse prediction", "t": 2},
{"a": "Field-aware factorization machines", "h": null, "d": "Click prediction", "t": 3},
{"a": "Wide and deep", "h": "Memorization plus generalization", "d": "Recommendation ranking", "t": 3},
{"a": "Neural collaborative filtering", "h": null, "d": "Recommendation", "t": 2},
{"a": "Two-tower retrieval", "h": "Dual-encoder dot product", "d": "Candidate retrieval", "t": 2},
{"a": "DeepFM", "h": "FM plus deep network", "d": "Click prediction", "t": 3},
{"a": "Session-based GRU4Rec", "h": null, "d": "Sequential recommendation", "t": 3},
{"a": "SASRec", "h": "Self-attentive sequences", "d": "Sequential recommendation", "t": 3},
{"a": "Content-based filtering", "h": "TF-IDF item profiles", "d": "Recommendation", "t": 2},
{"a": "Slope one", "h": null, "d": "Rating prediction", "t": 3},
{"a": "Association rule mining", "h": "Apriori candidate pruning", "d": "Market-basket analysis", "t": 1},
{"a": "FP-growth", "h": "Frequent-pattern tree", "d": "Frequent-itemset mining", "t": 2},
{"a": "ECLAT", "h": "Vertical tid-set intersection", "d": "Frequent-itemset mining", "t": 3},
{"a": "Multi-armed bandit recommendation", "h": "Thompson sampling", "d": "Exploration in recommendation", "t": 2},
{"a": "Propensity score matching", "h": null, "d": "Causal effect estimation", "t": 2},
{"a": "Inverse propensity weighting", "h": null, "d": "Causal effect estimation", "t": 2},
{"a": "Difference-in-differences", "h": null, "d": "Causal inference", "t": 2},
{"a": "Regression discontinuity", "h": "Threshold local comparison", "d": "Causal inference", "t": 3},
{"a": "Instrumental variables", "h": "Two-stage least squares", "d": "Causal inference", "t": 2},
{"a": "Synthetic control", "h": "Weighted donor pool", "d": "Causal inference", "t": 3},
{"a": "Doubly robust estimation", "h": null, "d": "Causal effect estimation", "t": 3},
{"a": "Causal forest", "h": "Honest-split trees", "d": "Heterogeneous treatment effects", "t": 3},
{"a": "T-learner", "h": "Separate outcome models", "d": "Treatment effect estimation", "t": 3},
{"a": "X-learner", "h": "Cross-fitted imputation", "d": "Treatment effect estimation", "t": 3},
{"a": "PC algorithm", "h": "Conditional-independence pruning", "d": "Causal structure discovery", "t": 3},
{"a": "Do-calculus identification", "h": null, "d": "Causal effect identification", "t": 3},
{"a": "Uplift modeling", "h": "Two-model difference", "d": "Treatment targeting", "t": 3},
{"a": "SHAP attribution", "h": "Shapley-value feature credit", "d": "Model explanation", "t": 2},
{"a": "LIME", "h": "Local surrogate model", "d": "Model explanation", "t": 2},
{"a": "Integrated gradients", "h": "Path-integral attribution", "d": "Model explanation", "t": 3},
{"a": "Counterfactual explanation", "h": "Nearest flipped instance", "d": "Model explanation", "t": 3},
{"a": "Conformal prediction", "h": "Nonconformity quantile", "d": "Uncertainty quantification", "t": 2},
{"a": "Platt scaling", "h": "Sigmoid calibration", "d": "Probability calibration", "t": 2},
{"a": "Isotonic calibration", "h": "Monotone regression", "d": "Probability calibration", "t": 3}
]
